{
  "name": "Beaver Warrior",
  "number": "32452818",
  "is_illegal": false,
  "text": "What this creature lacks in size it makes up for in defense when battling in the prairie.",
  "type": "Monster",
  "is_monster": true,
  "is_spell": false,
  "is_trap": false,
  "species": "Beast-Warrior",
  "attack": "1200",
  "defense": "1500",
  "attribute": "EARTH",
  "is_pendulum": false,
  "is_xyz": false,
  "is_synchro": false,
  "is_fusion": false,
  "is_link": false,
  "is_extra_deck": false,
  "monster_types": [
    "Normal"
  ],
  "stars": "4"
}