{
  "name": "Cipher Wing",
  "number": "81974607",
  "is_illegal": false,
  "text": "If you control a \"Cipher\" monster, you can Special Summon this card (from your hand). You can Tribute this card; increase the Levels of all \"Cipher\" monsters you control by 4 until the end of this turn.",
  "type": "Monster",
  "is_monster": true,
  "is_spell": false,
  "is_trap": false,
  "species": "Machine",
  "attack": "1400",
  "defense": "1200",
  "attribute": "LIGHT",
  "is_pendulum": false,
  "is_xyz": false,
  "is_synchro": false,
  "is_fusion": false,
  "is_link": false,
  "is_extra_deck": false,
  "monster_types": [
    "Effect"
  ],
  "stars": "4"
}