{
  "name": "Crystron Phoenix",
  "number": "2743001",
  "is_illegal": false,
  "text": "1 Tuner Synchro Monster + 1 or more non-Tuner Synchro Monsters\nIf this card is Synchro Summoned: You can banish all Spell and Trap Cards your opponent controls and in their Graveyard. If this Synchro Summoned card is destroyed by battle or card effect: You can target 1 other monster in your Graveyard; Special Summon it.",
  "type": "Monster",
  "is_monster": true,
  "is_spell": false,
  "is_trap": false,
  "species": "Machine",
  "attack": "2800",
  "defense": "2000",
  "attribute": "WATER",
  "is_pendulum": false,
  "is_xyz": false,
  "is_synchro": true,
  "is_fusion": false,
  "is_link": false,
  "is_extra_deck": true,
  "monster_types": [
    "Synchro"
  ],
  "stars": "9"
}