{
  "name": "Dragunity Brandistock",
  "number": "54455664",
  "is_illegal": false,
  "text": "While this card is equipped to a monster, that monster can attack twice during each Battle Phase.",
  "type": "Monster",
  "is_monster": true,
  "is_spell": false,
  "is_trap": false,
  "species": "Dragon",
  "attack": "600",
  "defense": "400",
  "attribute": "WIND",
  "is_pendulum": false,
  "is_xyz": false,
  "is_synchro": false,
  "is_fusion": false,
  "is_link": false,
  "is_extra_deck": false,
  "monster_types": [
    "Tuner"
  ],
  "stars": "1"
}