{
  "name": "Ghost Knight of Jackal",
  "number": "13386503",
  "is_illegal": false,
  "text": "You can Special Summon an opponent's monster that is destroyed and sent to the Graveyard by this card as a result of battle to your side of the field in face-up Defense Position.",
  "type": "Monster",
  "is_monster": true,
  "is_spell": false,
  "is_trap": false,
  "species": "Beast-Warrior",
  "attack": "1700",
  "defense": "1600",
  "attribute": "EARTH",
  "is_pendulum": false,
  "is_xyz": false,
  "is_synchro": false,
  "is_fusion": false,
  "is_link": false,
  "is_extra_deck": false,
  "monster_types": [
    "Effect"
  ],
  "stars": "5"
}