{
  "name": "Lightray Grepher",
  "number": "27407330",
  "is_illegal": false,
  "text": "You can Special Summon this card (from your hand) by discarding 1 Level 5 or higher LIGHT monster. Once per turn: You can discard 1 LIGHT monster; banish 1 LIGHT monster from your Deck.",
  "type": "Monster",
  "is_monster": true,
  "is_spell": false,
  "is_trap": false,
  "species": "Warrior",
  "attack": "1700",
  "defense": "1600",
  "attribute": "LIGHT",
  "is_pendulum": false,
  "is_xyz": false,
  "is_synchro": false,
  "is_fusion": false,
  "is_link": false,
  "is_extra_deck": false,
  "monster_types": [
    "Effect"
  ],
  "stars": "4"
}