{
  "name": "Machine Lord Ür",
  "number": "96938777",
  "is_illegal": false,
  "text": "This card can attack all monsters your opponent controls once each. If this card attacks or is attacked, your opponent takes no battle damage.",
  "type": "Monster",
  "is_monster": true,
  "is_spell": false,
  "is_trap": false,
  "species": "Machine",
  "attack": "1600",
  "defense": "1500",
  "attribute": "EARTH",
  "is_pendulum": false,
  "is_xyz": false,
  "is_synchro": false,
  "is_fusion": false,
  "is_link": false,
  "is_extra_deck": false,
  "monster_types": [
    "Effect"
  ],
  "stars": "4"
}