{
  "name": "Magical Reflect Slime",
  "number": "3918345",
  "is_illegal": false,
  "text": "This card is treated as a Normal Monster while face-up on the field or in the Graveyard. While this card is face-up on the field, you can Normal Summon it to have it be treated as an Effect Monster with this effect:\nâ—? Your opponent takes all Battle Damage that you would have taken from a battle involving this card.",
  "type": "Monster",
  "is_monster": true,
  "is_spell": false,
  "is_trap": false,
  "species": "Aqua",
  "attack": "700",
  "defense": "1200",
  "attribute": "WATER",
  "is_pendulum": false,
  "is_xyz": false,
  "is_synchro": false,
  "is_fusion": false,
  "is_link": false,
  "is_extra_deck": false,
  "monster_types": [
    "Gemini"
  ],
  "stars": "3"
}