{
  "name": "Major Riot",
  "number": "9074847",
  "is_illegal": false,
  "text": "You can activate this card when 1 or more of your monsters are returned from the field to your hand by your opponent's card effect. Return all Monster Cards on the field to your respective hands. Both you and your opponent then Special Summon from your hand the same number of Monster Cards on the field in face-down Defense Position.",
  "type": "Trap",
  "is_monster": false,
  "is_spell": false,
  "is_trap": true,
  "property": "Normal"
}