{
  "name": "Man Beast of Ares",
  "number": "71395725",
  "is_illegal": false,
  "text": "After a Chain (of 2 or more Links) resolves, this card gains 500 ATK.",
  "type": "Monster",
  "is_monster": true,
  "is_spell": false,
  "is_trap": false,
  "species": "Beast-Warrior",
  "attack": "500",
  "defense": "500",
  "attribute": "EARTH",
  "is_pendulum": false,
  "is_xyz": false,
  "is_synchro": false,
  "is_fusion": false,
  "is_link": false,
  "is_extra_deck": false,
  "monster_types": [
    "Effect"
  ],
  "stars": "3"
}