{
  "name": "Metalfoes Adamante",
  "number": "81612598",
  "is_illegal": false,
  "text": "1 \"Metalfoes\" monster + 1 monster with 2500 or less ATK",
  "type": "Monster",
  "is_monster": true,
  "is_spell": false,
  "is_trap": false,
  "species": "Psychic",
  "attack": "2500",
  "defense": "2500",
  "attribute": "FIRE",
  "is_pendulum": false,
  "is_xyz": false,
  "is_synchro": false,
  "is_fusion": true,
  "is_link": false,
  "is_extra_deck": true,
  "monster_types": [
    "Fusion"
  ],
  "stars": "5"
}