{
  "name": "Number 69: Heraldry Crest",
  "number": "2407234",
  "is_illegal": false,
  "text": "3 Level 4 monsters\nWhen this card is Special Summoned: Negate the effects of all other face-up Xyz Monsters currently on the field. You can target 1 other face-up Xyz Monster on the field; until the End Phase, this card's name and original effect become the same as that monster. You can only use this effect of \"Number 69: Heraldry Crest\" once per turn.",
  "type": "Monster",
  "is_monster": true,
  "is_spell": false,
  "is_trap": false,
  "species": "Psychic",
  "attack": "2600",
  "defense": "1400",
  "attribute": "LIGHT",
  "is_pendulum": false,
  "is_xyz": true,
  "is_synchro": false,
  "is_fusion": false,
  "is_link": false,
  "is_extra_deck": true,
  "monster_types": [
    "XYZ"
  ],
  "stars": "4"
}