{
  "name": "Spell Wall",
  "number": "84117021",
  "is_illegal": false,
  "text": "Activate 1 of these effects. Your opponent takes no further damage this turn.\nâ—? During this turn, no Summon of a Spellcaster-Type monster can be negated, and when a Spellcaster-Type monster is Summoned, your opponent cannot activate cards or effects.\nâ—? Target 1 Spellcaster-Type monster you control; if it attacks this turn, your opponent cannot activate cards or effects until the end of the Damage Step.",
  "type": "Spell",
  "is_monster": false,
  "is_spell": true,
  "is_trap": false,
  "property": "Normal"
}