{
  "name": "Super-Electromagnetic Voltech Dragon",
  "number": "20529766",
  "is_illegal": false,
  "text": "If you Tribute Summon this card by Tributing 1 of the following monsters, it gains the appropriate effect:\nâ—? Batteryman D: Negate the effect of a Spell or Trap Card that targets this 1 card.\nâ—? Batteryman C: During battle between this attacking card and a Defense Position monster whose DEF is lower than the ATK of this card, inflict the difference as Battle Damage to your opponent.\nâ—? Batteryman AA: This card gains 1000 ATK.",
  "type": "Monster",
  "is_monster": true,
  "is_spell": false,
  "is_trap": false,
  "species": "Thunder",
  "attack": "2400",
  "defense": "1000",
  "attribute": "LIGHT",
  "is_pendulum": false,
  "is_xyz": false,
  "is_synchro": false,
  "is_fusion": false,
  "is_link": false,
  "is_extra_deck": false,
  "monster_types": [
    "Effect"
  ],
  "stars": "5"
}