{
  "name": "Swamp Battleguard",
  "number": "40453765",
  "is_illegal": false,
  "text": "This card gains 500 ATK for each \"Lava Battleguard\" you control.",
  "type": "Monster",
  "is_monster": true,
  "is_spell": false,
  "is_trap": false,
  "species": "Warrior",
  "attack": "1800",
  "defense": "1500",
  "attribute": "EARTH",
  "is_pendulum": false,
  "is_xyz": false,
  "is_synchro": false,
  "is_fusion": false,
  "is_link": false,
  "is_extra_deck": false,
  "monster_types": [
    "Effect"
  ],
  "stars": "5"
}