{
  "name": "U.A. Perfect Ace",
  "number": "82419869",
  "is_illegal": false,
  "text": "You can Special Summon this card (from your hand) by returning 1 \"U.A.\" monster you control to the hand, except \"U.A. Perfect Ace\". You can only Special Summon \"U.A. Perfect Ace\" once per turn this way. Once per turn, during your opponent's turn, when a card or effect is activated: You can discard 1 card; negate that activation, and if you do, destroy it (this is a Quick Effect).",
  "type": "Monster",
  "is_monster": true,
  "is_spell": false,
  "is_trap": false,
  "species": "Warrior",
  "attack": "1500",
  "defense": "2500",
  "attribute": "EARTH",
  "is_pendulum": false,
  "is_xyz": false,
  "is_synchro": false,
  "is_fusion": false,
  "is_link": false,
  "is_extra_deck": false,
  "monster_types": [
    "Effect"
  ],
  "stars": "5"
}