{
  "name": "Vampiric Koala",
  "number": "1371589",
  "is_illegal": false,
  "text": "If this card inflicts battle damage to your opponent by battle with a monster: Gain LP equal to the battle damage inflicted.",
  "type": "Monster",
  "is_monster": true,
  "is_spell": false,
  "is_trap": false,
  "species": "Beast",
  "attack": "1800",
  "defense": "1500",
  "attribute": "EARTH",
  "is_pendulum": false,
  "is_xyz": false,
  "is_synchro": false,
  "is_fusion": false,
  "is_link": false,
  "is_extra_deck": false,
  "monster_types": [
    "Effect"
  ],
  "stars": "4"
}