{
  "status": "success",
  "set": {
    "name": "Fusion Enforcers",
    "type": "Booster Pack",
    "date": "2017-02-23",
    "distribution": "booster_pack",
    "prefix": "FUEN",
    "sub_sets": [],
    "load": true,
    "cards": [
      {
        "card_name": "Predaplant Sarraceniant",
        "set_number": "FUEN-EN001",
        "rarities": [
          "Super Rare"
        ],
        "count": {
          "Super Rare": 1
        }
      },
      {
        "card_name": "Predaplant Drosophyllum Hydra",
        "set_number": "FUEN-EN002",
        "rarities": [
          "Secret Rare"
        ],
        "count": {
          "Secret Rare": 1
        }
      },
      {
        "card_name": "Predaplant Pterapenthes",
        "set_number": "FUEN-EN003",
        "rarities": [
          "Super Rare"
        ],
        "count": {
          "Super Rare": 1
        }
      },
      {
        "card_name": "Predaplant Spinodionaea",
        "set_number": "FUEN-EN004",
        "rarities": [
          "Secret Rare"
        ],
        "count": {
          "Secret Rare": 1
        }
      },
      {
        "card_name": "Predaplant Chlamydosundew",
        "set_number": "FUEN-EN005",
        "rarities": [
          "Secret Rare"
        ],
        "count": {
          "Secret Rare": 1
        }
      },
      {
        "card_name": "Predaplant Flytrap",
        "set_number": "FUEN-EN006",
        "rarities": [
          "Super Rare"
        ],
        "count": {
          "Super Rare": 1
        }
      },
      {
        "card_name": "Predaplant Moray Nepenthes",
        "set_number": "FUEN-EN007",
        "rarities": [
          "Super Rare"
        ],
        "count": {
          "Super Rare": 1
        }
      },
      {
        "card_name": "Predaplant Squid Drosera",
        "set_number": "FUEN-EN008",
        "rarities": [
          "Super Rare"
        ],
        "count": {
          "Super Rare": 1
        }
      },
      {
        "card_name": "Predaplant Chimerafflesia",
        "set_number": "FUEN-EN009",
        "rarities": [
          "Secret Rare"
        ],
        "count": {
          "Secret Rare": 1
        }
      },
      {
        "card_name": "Greedy Venom Fusion Dragon",
        "set_number": "FUEN-EN010",
        "rarities": [
          "Secret Rare"
        ],
        "count": {
          "Secret Rare": 1
        }
      },
      {
        "card_name": "Predaponics",
        "set_number": "FUEN-EN011",
        "rarities": [
          "Secret Rare"
        ],
        "count": {
          "Secret Rare": 1
        }
      },
      {
        "card_name": "Predapruning",
        "set_number": "FUEN-EN012",
        "rarities": [
          "Super Rare"
        ],
        "count": {
          "Super Rare": 1
        }
      },
      {
        "card_name": "Predaplanet",
        "set_number": "FUEN-EN013",
        "rarities": [
          "Super Rare"
        ],
        "count": {
          "Super Rare": 1
        }
      },
      {
        "card_name": "Fluffal Octopus",
        "set_number": "FUEN-EN014",
        "rarities": [
          "Secret Rare"
        ],
        "count": {
          "Secret Rare": 1
        }
      },
      {
        "card_name": "Fluffal Penguin",
        "set_number": "FUEN-EN015",
        "rarities": [
          "Super Rare"
        ],
        "count": {
          "Super Rare": 1
        }
      },
      {
        "card_name": "Fluffal Dog",
        "set_number": "FUEN-EN016",
        "rarities": [
          "Super Rare"
        ],
        "count": {
          "Super Rare": 1
        }
      },
      {
        "card_name": "Fluffal Owl",
        "set_number": "FUEN-EN017",
        "rarities": [
          "Super Rare"
        ],
        "count": {
          "Super Rare": 1
        }
      },
      {
        "card_name": "Edge Imp Sabres",
        "set_number": "FUEN-EN018",
        "rarities": [
          "Super Rare"
        ],
        "count": {
          "Super Rare": 1
        }
      },
      {
        "card_name": "Edge Imp Chain",
        "set_number": "FUEN-EN019",
        "rarities": [
          "Super Rare"
        ],
        "count": {
          "Super Rare": 1
        }
      },
      {
        "card_name": "Frightfur Kraken",
        "set_number": "FUEN-EN020",
        "rarities": [
          "Secret Rare"
        ],
        "count": {
          "Secret Rare": 1
        }
      },
      {
        "card_name": "Frightfur Wolf",
        "set_number": "FUEN-EN021",
        "rarities": [
          "Super Rare"
        ],
        "count": {
          "Super Rare": 1
        }
      },
      {
        "card_name": "Frightfur Tiger",
        "set_number": "FUEN-EN022",
        "rarities": [
          "Secret Rare"
        ],
        "count": {
          "Secret Rare": 1
        }
      },
      {
        "card_name": "Frightfur Sheep",
        "set_number": "FUEN-EN023",
        "rarities": [
          "Super Rare"
        ],
        "count": {
          "Super Rare": 1
        }
      },
      {
        "card_name": "Toy Vendor",
        "set_number": "FUEN-EN024",
        "rarities": [
          "Super Rare"
        ],
        "count": {
          "Super Rare": 1
        }
      },
      {
        "card_name": "Frightfur Fusion",
        "set_number": "FUEN-EN025",
        "rarities": [
          "Super Rare"
        ],
        "count": {
          "Super Rare": 1
        }
      },
      {
        "card_name": "Aleister the Invoker",
        "set_number": "FUEN-EN026",
        "rarities": [
          "Super Rare"
        ],
        "count": {
          "Super Rare": 1
        }
      },
      {
        "card_name": "Invoked Caliga",
        "set_number": "FUEN-EN027",
        "rarities": [
          "Secret Rare"
        ],
        "count": {
          "Secret Rare": 1
        }
      },
      {
        "card_name": "Invoked Raidjin",
        "set_number": "FUEN-EN028",
        "rarities": [
          "Secret Rare"
        ],
        "count": {
          "Secret Rare": 1
        }
      },
      {
        "card_name": "Invoked Cocytus",
        "set_number": "FUEN-EN029",
        "rarities": [
          "Secret Rare"
        ],
        "count": {
          "Secret Rare": 1
        }
      },
      {
        "card_name": "Invoked Purgatrio",
        "set_number": "FUEN-EN030",
        "rarities": [
          "Secret Rare"
        ],
        "count": {
          "Secret Rare": 1
        }
      },
      {
        "card_name": "Invoked Magellanica",
        "set_number": "FUEN-EN031",
        "rarities": [
          "Secret Rare"
        ],
        "count": {
          "Secret Rare": 1
        }
      },
      {
        "card_name": "Invoked Mechaba",
        "set_number": "FUEN-EN032",
        "rarities": [
          "Secret Rare"
        ],
        "count": {
          "Secret Rare": 1
        }
      },
      {
        "card_name": "Invoked Elysium",
        "set_number": "FUEN-EN033",
        "rarities": [
          "Secret Rare"
        ],
        "count": {
          "Secret Rare": 1
        }
      },
      {
        "card_name": "Magical Meltdown",
        "set_number": "FUEN-EN034",
        "rarities": [
          "Secret Rare"
        ],
        "count": {
          "Secret Rare": 1
        }
      },
      {
        "card_name": "Invocation",
        "set_number": "FUEN-EN035",
        "rarities": [
          "Secret Rare"
        ],
        "count": {
          "Secret Rare": 1
        }
      },
      {
        "card_name": "The Book of the Law",
        "set_number": "FUEN-EN036",
        "rarities": [
          "Secret Rare"
        ],
        "count": {
          "Secret Rare": 1
        }
      },
      {
        "card_name": "Omega Summon",
        "set_number": "FUEN-EN037",
        "rarities": [
          "Secret Rare"
        ],
        "count": {
          "Secret Rare": 1
        }
      },
      {
        "card_name": "Summoner of Illusions",
        "set_number": "FUEN-EN038",
        "rarities": [
          "Super Rare"
        ],
        "count": {
          "Super Rare": 1
        }
      },
      {
        "card_name": "Summoner Monk",
        "set_number": "FUEN-EN039",
        "rarities": [
          "Super Rare"
        ],
        "count": {
          "Super Rare": 1
        }
      },
      {
        "card_name": "King of the Swamp",
        "set_number": "FUEN-EN040",
        "rarities": [
          "Super Rare"
        ],
        "count": {
          "Super Rare": 1
        }
      },
      {
        "card_name": "Fusion Substitute",
        "set_number": "FUEN-EN041",
        "rarities": [
          "Super Rare"
        ],
        "count": {
          "Super Rare": 1
        }
      },
      {
        "card_name": "Instant Fusion",
        "set_number": "FUEN-EN042",
        "rarities": [
          "Super Rare"
        ],
        "count": {
          "Super Rare": 1
        }
      },
      {
        "card_name": "Fusion Recovery",
        "set_number": "FUEN-EN043",
        "rarities": [
          "Super Rare"
        ],
        "count": {
          "Super Rare": 1
        }
      },
      {
        "card_name": "Phoenix Wing Wind Blast",
        "set_number": "FUEN-EN044",
        "rarities": [
          "Super Rare"
        ],
        "count": {
          "Super Rare": 1
        }
      },
      {
        "card_name": "Homunculus the Alchemic Being",
        "set_number": "FUEN-EN045",
        "rarities": [
          "Super Rare"
        ],
        "count": {
          "Super Rare": 1
        }
      },
      {
        "card_name": "Lonefire Blossom",
        "set_number": "FUEN-EN046",
        "rarities": [
          "Super Rare"
        ],
        "count": {
          "Super Rare": 1
        }
      },
      {
        "card_name": "Elemental HERO Prisma",
        "set_number": "FUEN-EN047",
        "rarities": [
          "Super Rare"
        ],
        "count": {
          "Super Rare": 1
        }
      },
      {
        "card_name": "Performapal Trump Witch",
        "set_number": "FUEN-EN048",
        "rarities": [
          "Super Rare"
        ],
        "count": {
          "Super Rare": 1
        }
      },
      {
        "card_name": "Polymerization",
        "set_number": "FUEN-EN049",
        "rarities": [
          "Super Rare"
        ],
        "count": {
          "Super Rare": 1
        }
      },
      {
        "card_name": "Fusion Gate",
        "set_number": "FUEN-EN050",
        "rarities": [
          "Super Rare"
        ],
        "count": {
          "Super Rare": 1
        }
      },
      {
        "card_name": "Re-Fusion",
        "set_number": "FUEN-EN051",
        "rarities": [
          "Super Rare"
        ],
        "count": {
          "Super Rare": 1
        }
      },
      {
        "card_name": "Branch!",
        "set_number": "FUEN-EN052",
        "rarities": [
          "Super Rare"
        ],
        "count": {
          "Super Rare": 1
        }
      },
      {
        "card_name": "Miracle Fertilizer",
        "set_number": "FUEN-EN053",
        "rarities": [
          "Super Rare"
        ],
        "count": {
          "Super Rare": 1
        }
      },
      {
        "card_name": "Mark of the Rose",
        "set_number": "FUEN-EN054",
        "rarities": [
          "Super Rare"
        ],
        "count": {
          "Super Rare": 1
        }
      },
      {
        "card_name": "Super Solar Nutrient",
        "set_number": "FUEN-EN055",
        "rarities": [
          "Super Rare"
        ],
        "count": {
          "Super Rare": 1
        }
      },
      {
        "card_name": "Battle Fusion",
        "set_number": "FUEN-EN056",
        "rarities": [
          "Super Rare"
        ],
        "count": {
          "Super Rare": 1
        }
      },
      {
        "card_name": "Fusion Conscription",
        "set_number": "FUEN-EN057",
        "rarities": [
          "Super Rare"
        ],
        "count": {
          "Super Rare": 1
        }
      },
      {
        "card_name": "Paradox Fusion",
        "set_number": "FUEN-EN058",
        "rarities": [
          "Super Rare"
        ],
        "count": {
          "Super Rare": 1
        }
      },
      {
        "card_name": "Grisaille Prison",
        "set_number": "FUEN-EN059",
        "rarities": [
          "Super Rare"
        ],
        "count": {
          "Super Rare": 1
        }
      },
      {
        "card_name": "Fusion Reserve",
        "set_number": "FUEN-EN060",
        "rarities": [
          "Super Rare"
        ],
        "count": {
          "Super Rare": 1
        }
      }
    ]
  }
}